{"iI0J2/0l4Y+4wa3wZQSz/Q==":"imgp6019-2000x2000.jpg","2B7y9gq2+Gv2EpWEnXDlhg==":"imgp6488-2000x2000.jpg","RB5prjTKHRiNyPZHoYHNnA==":"imgp6710-2000x1328.jpg","2tsucFADaU1uUCPgxjD3Cw==":"imgp6755-2000x3011.jpg","j7wUDLO3uPTPxLiJR+xM3w==":"imgp6371-2000x1328.jpg","9AucocLqyTFMJypU2ct3rA==":"imgp8538-2000x1328.jpg","FRLvZ3TAr4EqcluDXWC7tQ==":"imgp2375-2000x2000.jpg","VHmVetxNMJOJ6ebc8ffM1g==":"imgp2362-2000x1328.jpg","P/eBfca/2F+i4xNnExHVWA==":"imgp1122-2000x1328.jpg","9WImbf97/G9U7FfCtd/gZQ==":"imgp6355-2000x3011.jpg","EvcshWzy/SxtqIAGySzenQ==":"imgp6049-2000x3011.jpg","jfK1WuoIswQcfYWS5pcN0Q==":"imgp8909-2000x3011.jpg","yktNxQmeWLXtt7F7iWrMZA==":"04021106-2000x2985.jpg","09zyBd1iAWVveeaJvw/Z2Q==":"imgp6971-2000x3011.jpg","DSS6ORJbPvGyflT8wCz4UQ==":"imgp7912-2000x3012.jpg","SMyW7IOeItEZ4Fwda2so2g==":"imgp6949-2000x3011.jpg","Q7XTz5ia/tVvjtkoIMDUBA==":"imgp7900-2000x3011.jpg","b7Zyi+pOjHEJjIpAFscjSA==":"imgp6476-2000x2000.jpg","cxxIkwg0DKb7K207dlnkHQ==":"imgp6489-2000x2000.jpg","oCC5wN7246kevU1XkpXAIQ==":"imgp6490-2000x2000.jpg","/qMltcWxStuupi0aU/sF3w==":"imgp6019-1400x1400.jpg","hmvRFLwwbgcdMCZGyQ8UIg==":"imgp6426-2000x1679.jpg","TQzWOTqbOHGaw4Qec+Oxtw==":"imgp6712-2000x1328.jpg","Or/WFz2WhLAWcBSNYWqxrw==":"imgp6821-2000x1328.jpg","I9+1hkf5u2aS7qVdYwYUaw==":"imgp7095-2000x1488.jpg","ot7MQR2NrLRwcrn70CH/kQ==":"logo-fie.gif","VbmVdZ/h9o3I16BwWoj6wQ==":"untitled.png","RV0HW0EhZwjC8AW53Atknw==":"untitled-1.png","waSqmXkaztGGw6oJg3cvBQ==":"untitled-2.png","0hFj1pGptzrZzEcVC/IP+A==":"untitled-3.png"}